opentelemetry/sdk/__init__.pyi
opentelemetry/sdk/py.typed
opentelemetry/sdk/_configuration/__init__.py
opentelemetry/sdk/_events/__init__.py
opentelemetry/sdk/_logs/__init__.py
opentelemetry/sdk/_logs/_internal/__init__.py
opentelemetry/sdk/_logs/_internal/export/__init__.py
opentelemetry/sdk/_logs/_internal/export/in_memory_log_exporter.py
opentelemetry/sdk/_logs/export/__init__.py
opentelemetry/sdk/environment_variables/__init__.py
opentelemetry/sdk/error_handler/__init__.py
opentelemetry/sdk/metrics/__init__.py
opentelemetry/sdk/metrics/_internal/__init__.py
opentelemetry/sdk/metrics/_internal/_view_instrument_match.py
opentelemetry/sdk/metrics/_internal/aggregation.py
opentelemetry/sdk/metrics/_internal/exceptions.py
opentelemetry/sdk/metrics/_internal/instrument.py
opentelemetry/sdk/metrics/_internal/measurement.py
opentelemetry/sdk/metrics/_internal/measurement_consumer.py
opentelemetry/sdk/metrics/_internal/metric_reader_storage.py
opentelemetry/sdk/metrics/_internal/point.py
opentelemetry/sdk/metrics/_internal/sdk_configuration.py
opentelemetry/sdk/metrics/_internal/view.py
opentelemetry/sdk/metrics/_internal/exemplar/__init__.py
opentelemetry/sdk/metrics/_internal/exemplar/exemplar.py
opentelemetry/sdk/metrics/_internal/exemplar/exemplar_filter.py
opentelemetry/sdk/metrics/_internal/exemplar/exemplar_reservoir.py
opentelemetry/sdk/metrics/_internal/exponential_histogram/__init__.py
opentelemetry/sdk/metrics/_internal/exponential_histogram/buckets.py
opentelemetry/sdk/metrics/_internal/exponential_histogram/mapping/__init__.py
opentelemetry/sdk/metrics/_internal/exponential_histogram/mapping/errors.py
opentelemetry/sdk/metrics/_internal/exponential_histogram/mapping/exponent_mapping.py
opentelemetry/sdk/metrics/_internal/exponential_histogram/mapping/ieee_754.md
opentelemetry/sdk/metrics/_internal/exponential_histogram/mapping/ieee_754.py
opentelemetry/sdk/metrics/_internal/exponential_histogram/mapping/logarithm_mapping.py
opentelemetry_multi_ten_sdk-1.30.0.dist-info/METADATA
opentelemetry_multi_ten_sdk-1.30.0.dist-info/WHEEL
opentelemetry_multi_ten_sdk-1.30.0.dist-info/entry_points.txt
opentelemetry_multi_ten_sdk-1.30.0.dist-info/licenses/LICENSE
opentelemetry_multi_ten_sdk-1.30.0.dist-info/RECORD
