Metadata-Version: 2.4
Name: opentelemetry-multi-ten-sdk
Version: 1.30.0
Summary: OpenTelemetry Python SDK
Project-URL: Homepage, https://github.com/open-telemetry/opentelemetry-python/tree/main/opentelemetry-sdk
Project-URL: Repository, https://github.com/open-telemetry/opentelemetry-python
Author-email: OpenTelemetry Authors <cncf-opentelemetry-contributors@lists.cncf.io>
License: Apache-2.0
License-File: LICENSE
Classifier: Development Status :: 5 - Production/Stable
Classifier: Framework :: OpenTelemetry
Classifier: Intended Audience :: Developers
Classifier: License :: OSI Approved :: Apache Software License
Classifier: Programming Language :: Python
Classifier: Programming Language :: Python :: 3
Classifier: Programming Language :: Python :: 3.8
Classifier: Programming Language :: Python :: 3.9
Classifier: Programming Language :: Python :: 3.10
Classifier: Programming Language :: Python :: 3.11
Classifier: Programming Language :: Python :: 3.12
Classifier: Programming Language :: Python :: 3.13
Classifier: Typing :: Typed
Requires-Python: >=3.8
Requires-Dist: opentelemetry-api==1.30.0
Requires-Dist: opentelemetry-semantic-conventions==0.51b0
Requires-Dist: typing-extensions>=3.7.4
